nowlibcraw/Dicts.py
nowlibcraw/PostSummaryTweet.py
nowlibcraw/PostTweet.py
nowlibcraw/TulipsGetNewResource.py
nowlibcraw/_GetNewResource.py
nowlibcraw/__init__.py
nowlibcraw/main.py
nowlibcraw/py.typed
nowlibcraw-1.0.0.dist-info/LICENSE.txt
nowlibcraw-1.0.0.dist-info/METADATA
nowlibcraw-1.0.0.dist-info/WHEEL
nowlibcraw-1.0.0.dist-info/entry_points.txt
nowlibcraw-1.0.0.dist-info/top_level.txt
nowlibcraw-1.0.0.dist-info/RECORD
