Metadata-Version: 2.1
Name: nowlibcraw
Version: 1.0.0
Summary: Obtaining information about new materials from the library system
Home-page: https://github.com/eggplants/nowlibcraw
Author: eggplants
Author-email: w10776e8w@yahoo.co.jp
License: MIT
Platform: UNKNOWN
Classifier: License :: OSI Approved :: MIT License
Classifier: Programming Language :: Python
Classifier: Programming Language :: Python :: 3
Classifier: Programming Language :: Python :: 3 :: Only
Classifier: Programming Language :: Python :: 3.7
Classifier: Programming Language :: Python :: 3.8
Classifier: Programming Language :: Python :: 3.9
Classifier: Programming Language :: Python :: 3.10
Classifier: Programming Language :: Python :: Implementation :: CPython
Requires-Python: >=3.7
License-File: LICENSE.txt
Requires-Dist: beautifulsoup4 (>=4.10.0)
Requires-Dist: lxml (>=4.8.0)
Requires-Dist: pyppeteer (>=1.0.2)
Requires-Dist: python-dotenv (>=0.19.2)
Requires-Dist: requests (>=2.26.0)
Requires-Dist: tweepy (>=4.6.0)
Requires-Dist: types-beautifulsoup4 (>=4.10.14)
Requires-Dist: types-requests
Provides-Extra: dev
Requires-Dist: black ; extra == 'dev'
Requires-Dist: flake8 ; extra == 'dev'
Requires-Dist: mypy ; extra == 'dev'
Requires-Dist: setuptools (>=46.4.0) ; extra == 'dev'
Requires-Dist: types-setuptools ; extra == 'dev'
